bbbmeetings/__init__.py
bbbmeetings/bbbmeetings.py
bbbmeetings/connection.py
bbbmeetings/helpers.py
bbbmeetings/types.py
bbbmeetings-0.1.5.dist-info/WHEEL
bbbmeetings-0.1.5.dist-info/METADATA
bbbmeetings-0.1.5.dist-info/RECORD
