Metadata-Version: 2.1
Name: bbbmeetings
Version: 0.1.5
Summary: A module for reading bbb meetings from bbb servers
License: GPL-3.0+
Author: David Huss
Author-email: david.huss@hfbk-hamburg.de
Maintainer: David Huss
Maintainer-email: david.huss@hfbk-hamburg.de
Requires-Python: >=3.5,<4.0
Classifier: Development Status :: 4 - Beta
Classifier: License :: Free For Educational Use
Classifier: License :: Free for non-commercial use
Classifier: License :: OSI Approved :: GNU General Public License v3 (GPLv3)
Classifier: License :: OSI Approved :: GNU General Public License v3 or later (GPLv3+)
Classifier: Natural Language :: English
Classifier: Programming Language :: Python :: 3
Classifier: Programming Language :: Python :: 3.5
Classifier: Programming Language :: Python :: 3.6
Classifier: Programming Language :: Python :: 3.7
Classifier: Programming Language :: Python :: 3.8
Classifier: Programming Language :: Python :: 3.9
Classifier: Topic :: Communications :: Conferencing
Classifier: Topic :: Software Development :: Libraries :: Python Modules
Classifier: Topic :: System :: Monitoring
Requires-Dist: requests (>=2.25.1,<3.0.0)
Requires-Dist: xmltodict (>=0.12.0,<0.13.0)
